ctns/__init__.py
ctns/contact_network_simulator.py
ctns/generator.py
ctns/steps.py
ctns/utility.py
ctns-1.0.1.data/scripts/ctns
ctns-1.0.1.data/scripts/ctns.bat
ctns-1.0.1.data/scripts/ctns_run.py
ctns-1.0.1.dist-info/LICENSE.txt
ctns-1.0.1.dist-info/METADATA
ctns-1.0.1.dist-info/WHEEL
ctns-1.0.1.dist-info/top_level.txt
ctns-1.0.1.dist-info/RECORD
