Metadata-Version: 2.1
Name: ctns
Version: 1.0.1
Summary: CTNS, Contact Tracing Network Simulator: a tool to simulate contact tracing in a population where a disease is spreading
Home-page: https://gitlab.com/mistrello96/ctns
Author: Matteo Mistri, Diego Miglio
Author-email: matteo.mistri1996@gmail.com
License: GNU GPLv3
Download-URL: https://pypi.org/project/ctns/
Platform: UNKNOWN
Requires-Dist: python-igraph
Requires-Dist: numpy
Requires-Dist: pathlib
